getSecrets/__init__.py
getwixsecrets-1.0.2.dist-info/licenses/LICENSE
getwixsecrets-1.0.2.dist-info/METADATA
getwixsecrets-1.0.2.dist-info/WHEEL
getwixsecrets-1.0.2.dist-info/top_level.txt
getwixsecrets-1.0.2.dist-info/RECORD
