Metadata-Version: 2.4
Name: getWixSecrets
Version: 1.0.2
Summary: A package to read secrets from WIX site secrets or from a local file
Author-email: Xavier Mayeur <xavier@mayeur.be>
Project-URL: Homepage, https://github.com/icambristi/getWIXSecrets
Project-URL: Bug Tracker, https://github.com/icambrsiti/getWIXSecrets/issues
Classifier: Programming Language :: Python :: 3
Classifier: License :: OSI Approved :: MIT License
Classifier: Operating System :: OS Independent
Requires-Python: >=3.7
License-File: LICENSE
Requires-Dist: pyyaml
Requires-Dist: requests
Dynamic: license-file
